usu-0.1.0.dist-info/METADATA
usu-0.1.0.dist-info/WHEEL
usu-0.1.0.dist-info/licenses/LICENSE
usu/__init__.py
usu/_lexer.py
usu/_parser.py
usu/_version.py
usu/main.py
usu-0.1.0.dist-info/RECORD
