Metadata-Version: 2.1
Name: usu
Version: 0.1.0
Summary: usu parser/writer
Author-Email: Daylin Morgan <daylinmorgan@gmail.com>
License: MIT
Requires-Python: >=3.8
